djangotheming-0.1.0.dist-info/DESCRIPTION.rst
djangotheming-0.1.0.dist-info/METADATA
djangotheming-0.1.0.dist-info/RECORD
djangotheming-0.1.0.dist-info/WHEEL
djangotheming-0.1.0.dist-info/metadata.json
djangotheming-0.1.0.dist-info/top_level.txt
theming/__init__.py
theming/admin.py
theming/apps.py
theming/core.py
theming/exceptions.py
theming/middleware.py
theming/models.py
theming/thread_locals.py
theming/migrations/0001_initial.py
theming/migrations/__init__.py
theming/static/__init__.py
theming/static/finders.py
theming/static/storage.py
theming/template/__init__.py
theming/template/loaders/__init__.py
theming/template/loaders/theme.py
