Metadata-Version: 1.1
Name: djangotheming
Version: 0.1.0
Summary: Complete solution for theming your django site.
Home-page: https://github.com/saleem-latif/djangotheming
Author: Saleem Latif
Author-email: saleem_ee@hotmail.com
License: GPL 3.0
Keywords: Django Theming
Platform: UNKNOWN
Classifier: Development Status :: 3 - Alpha
Classifier: Framework :: Django
Classifier: Framework :: Django :: 1.8
Classifier: Framework :: Django :: 1.9
Classifier: Framework :: Django :: 1.10
Classifier: Framework :: Django :: 1.11
Classifier: Intended Audience :: Developers
Classifier: License :: OSI Approved :: GNU General Public License (GPL)
Classifier: Natural Language :: English
Classifier: Programming Language :: Python
Classifier: Programming Language :: Python :: 2
Classifier: Programming Language :: Python :: 2.7
Classifier: Programming Language :: Python :: 3
Classifier: Programming Language :: Python :: 3.5
